{
 "__fileName__": "base/meta/MarkerSet/Cave_Root_CN00_01 (VFX).mrk",
 "__snoID__": 1563246,
 "__type__": "MarkerSetDefinition",
 "__typeHash__": 4093179991,
 "tMarkerSet": [
  {
   "__type__": "Marker",
   "__typeHash__": 3132676386,
   "dwHash": 550982008,
   "nID": 3,
   "eType": 0,
   "transform": {
    "__type__": "PRTransform",
    "__typeHash__": 2588169118,
    "q": {
     "__type__": "bcQuat",
     "__typeHash__": 3955716320,
     "x": 0,
     "y": 0,
     "z": 0,
     "w": 1
    },
    "wp": {
     "x": 6.956470012664795,
     "y": 6.786230087280273,
     "z": 7.991980075836182
    }
   },
   "snoname": {
    "__raw__": 371004,
    "__group__": 14,
    "__type__": "DT_SNO_NAME",
    "__typeHash__": 3339108615,
    "__targetFileName__": "base/meta/EffectGroup/environmentVFX_water_aoeDrip.efg",
    "groupName": "EffectGroup",
    "name": "environmentVFX_water_aoeDrip"
   },
   "dwMarkerFlags": 0,
   "dwMarkerFlagsEx": 0,
   "vecScale": {
    "x": 1,
    "y": 1,
    "z": 1
   },
   "ptBase": [
    {
     "__type__": "MarkerEffectGroupData",
     "__typeHash__": 1385267894,
     "dwType": 1385267894,
     "dwPad": 0,
     "dwMarkerEffectGroupFlags": 0,
     "unk_4bf3f6b": 0,
     "unk_9411612": 0,
     "ptRunTimeMaterialValues": []
    }
   ],
   "ptGroupData": [],
   "ptMarkerLinks": [],
   "unk_c339f69": -1,
   "tIGCHideSettings": {
    "__type__": "MarkerIGCHideSettings",
    "__typeHash__": 867785856,
    "nHideGroup": 0,
    "dwFlags": 0
   },
   "dwSeed": 0,
   "tPrefabData": {
    "__type__": "PrefabData",
    "__typeHash__": 3988626058,
    "dwFlags": 0,
    "eOverrideFadeSettings": 0,
    "eFadeMethod": 0,
    "nFadeGroup": 0,
    "tIGCHideSettings": {
     "__type__": "MarkerIGCHideSettings",
     "__typeHash__": 867785856,
     "nHideGroup": 0,
     "dwFlags": 0
    },
    "eNavBehavior": 0,
    "eCullingLevel": 0,
    "szLookOverride": 0,
    "dwShaderMapOverride": 4294967295,
    "ptRunTimeMaterialValues": []
   }
  },
  {
   "__type__": "Marker",
   "__typeHash__": 3132676386,
   "dwHash": 550982009,
   "nID": 4,
   "eType": 0,
   "transform": {
    "__type__": "PRTransform",
    "__typeHash__": 2588169118,
    "q": {
     "__type__": "bcQuat",
     "__typeHash__": 3955716320,
     "x": 0,
     "y": 0,
     "z": -0.5372996926307678,
     "w": 0.8433914184570312
    },
    "wp": {
     "x": 7.043139934539795,
     "y": 17.5137996673584,
     "z": 8.569239616394043
    }
   },
   "snoname": {
    "__raw__": 371004,
    "__group__": 14,
    "__type__": "DT_SNO_NAME",
    "__typeHash__": 3339108615,
    "__targetFileName__": "base/meta/EffectGroup/environmentVFX_water_aoeDrip.efg",
    "groupName": "EffectGroup",
    "name": "environmentVFX_water_aoeDrip"
   },
   "dwMarkerFlags": 0,
   "dwMarkerFlagsEx": 0,
   "vecScale": {
    "x": 1,
    "y": 1,
    "z": 1
   },
   "ptBase": [
    {
     "__type__": "MarkerEffectGroupData",
     "__typeHash__": 1385267894,
     "dwType": 1385267894,
     "dwPad": 0,
     "dwMarkerEffectGroupFlags": 0,
     "unk_4bf3f6b": 0,
     "unk_9411612": 0,
     "ptRunTimeMaterialValues": []
    }
   ],
   "ptGroupData": [],
   "ptMarkerLinks": [],
   "unk_c339f69": -1,
   "tIGCHideSettings": {
    "__type__": "MarkerIGCHideSettings",
    "__typeHash__": 867785856,
    "nHideGroup": 0,
    "dwFlags": 0
   },
   "dwSeed": 0,
   "tPrefabData": {
    "__type__": "PrefabData",
    "__typeHash__": 3988626058,
    "dwFlags": 0,
    "eOverrideFadeSettings": 0,
    "eFadeMethod": 0,
    "nFadeGroup": 0,
    "tIGCHideSettings": {
     "__type__": "MarkerIGCHideSettings",
     "__typeHash__": 867785856,
     "nHideGroup": 0,
     "dwFlags": 0
    },
    "eNavBehavior": 0,
    "eCullingLevel": 0,
    "szLookOverride": 0,
    "dwShaderMapOverride": 4294967295,
    "ptRunTimeMaterialValues": []
   }
  },
  {
   "__type__": "Marker",
   "__typeHash__": 3132676386,
   "dwHash": 550982010,
   "nID": 5,
   "eType": 0,
   "transform": {
    "__type__": "PRTransform",
    "__typeHash__": 2588169118,
    "q": {
     "__type__": "bcQuat",
     "__typeHash__": 3955716320,
     "x": 0,
     "y": 0,
     "z": -0.17364813387393951,
     "w": 0.9848078489303589
    },
    "wp": {
     "x": 18.40329933166504,
     "y": 13.81820011138916,
     "z": 7.876949787139893
    }
   },
   "snoname": {
    "__raw__": 371004,
    "__group__": 14,
    "__type__": "DT_SNO_NAME",
    "__typeHash__": 3339108615,
    "__targetFileName__": "base/meta/EffectGroup/environmentVFX_water_aoeDrip.efg",
    "groupName": "EffectGroup",
    "name": "environmentVFX_water_aoeDrip"
   },
   "dwMarkerFlags": 0,
   "dwMarkerFlagsEx": 0,
   "vecScale": {
    "x": 1,
    "y": 1,
    "z": 1
   },
   "ptBase": [
    {
     "__type__": "MarkerEffectGroupData",
     "__typeHash__": 1385267894,
     "dwType": 1385267894,
     "dwPad": 0,
     "dwMarkerEffectGroupFlags": 0,
     "unk_4bf3f6b": 0,
     "unk_9411612": 0,
     "ptRunTimeMaterialValues": []
    }
   ],
   "ptGroupData": [],
   "ptMarkerLinks": [],
   "unk_c339f69": -1,
   "tIGCHideSettings": {
    "__type__": "MarkerIGCHideSettings",
    "__typeHash__": 867785856,
    "nHideGroup": 0,
    "dwFlags": 0
   },
   "dwSeed": 0,
   "tPrefabData": {
    "__type__": "PrefabData",
    "__typeHash__": 3988626058,
    "dwFlags": 0,
    "eOverrideFadeSettings": 0,
    "eFadeMethod": 0,
    "nFadeGroup": 0,
    "tIGCHideSettings": {
     "__type__": "MarkerIGCHideSettings",
     "__typeHash__": 867785856,
     "nHideGroup": 0,
     "dwFlags": 0
    },
    "eNavBehavior": 0,
    "eCullingLevel": 0,
    "szLookOverride": 0,
    "dwShaderMapOverride": 4294967295,
    "ptRunTimeMaterialValues": []
   }
  },
  {
   "__type__": "Marker",
   "__typeHash__": 3132676386,
   "dwHash": 550982011,
   "nID": 6,
   "eType": 0,
   "transform": {
    "__type__": "PRTransform",
    "__typeHash__": 2588169118,
    "q": {
     "__type__": "bcQuat",
     "__typeHash__": 3955716320,
     "x": 0,
     "y": 0,
     "z": -0.7660441994667053,
     "w": 0.6427879333496094
    },
    "wp": {
     "x": 5.6479902267456055,
     "y": 22.200199127197266,
     "z": 7.137209892272949
    }
   },
   "snoname": {
    "__raw__": 371004,
    "__group__": 14,
    "__type__": "DT_SNO_NAME",
    "__typeHash__": 3339108615,
    "__targetFileName__": "base/meta/EffectGroup/environmentVFX_water_aoeDrip.efg",
    "groupName": "EffectGroup",
    "name": "environmentVFX_water_aoeDrip"
   },
   "dwMarkerFlags": 0,
   "dwMarkerFlagsEx": 0,
   "vecScale": {
    "x": 1,
    "y": 1,
    "z": 1
   },
   "ptBase": [
    {
     "__type__": "MarkerEffectGroupData",
     "__typeHash__": 1385267894,
     "dwType": 1385267894,
     "dwPad": 0,
     "dwMarkerEffectGroupFlags": 0,
     "unk_4bf3f6b": 0,
     "unk_9411612": 0,
     "ptRunTimeMaterialValues": []
    }
   ],
   "ptGroupData": [],
   "ptMarkerLinks": [],
   "unk_c339f69": -1,
   "tIGCHideSettings": {
    "__type__": "MarkerIGCHideSettings",
    "__typeHash__": 867785856,
    "nHideGroup": 0,
    "dwFlags": 0
   },
   "dwSeed": 0,
   "tPrefabData": {
    "__type__": "PrefabData",
    "__typeHash__": 3988626058,
    "dwFlags": 0,
    "eOverrideFadeSettings": 0,
    "eFadeMethod": 0,
    "nFadeGroup": 0,
    "tIGCHideSettings": {
     "__type__": "MarkerIGCHideSettings",
     "__typeHash__": 867785856,
     "nHideGroup": 0,
     "dwFlags": 0
    },
    "eNavBehavior": 0,
    "eCullingLevel": 0,
    "szLookOverride": 0,
    "dwShaderMapOverride": 4294967295,
    "ptRunTimeMaterialValues": []
   }
  },
  {
   "__type__": "Marker",
   "__typeHash__": 3132676386,
   "dwHash": 2748734516,
   "nID": 7,
   "eType": 0,
   "transform": {
    "__type__": "PRTransform",
    "__typeHash__": 2588169118,
    "q": {
     "__type__": "bcQuat",
     "__typeHash__": 3955716320,
     "x": 0,
     "y": 0,
     "z": 0.9396926164627075,
     "w": -0.342020183801651
    },
    "wp": {
     "x": 23.480100631713867,
     "y": 7.593080043792725,
     "z": 7.74330997467041
    }
   },
   "snoname": {
    "__raw__": 1102492,
    "__group__": 14,
    "__type__": "DT_SNO_NAME",
    "__typeHash__": 3339108615,
    "__targetFileName__": "base/meta/EffectGroup/environmentVFX_water_aoeDrip_heavy.efg",
    "groupName": "EffectGroup",
    "name": "environmentVFX_water_aoeDrip_heavy"
   },
   "dwMarkerFlags": 0,
   "dwMarkerFlagsEx": 0,
   "vecScale": {
    "x": 1,
    "y": 1,
    "z": 1
   },
   "ptBase": [
    {
     "__type__": "MarkerEffectGroupData",
     "__typeHash__": 1385267894,
     "dwType": 1385267894,
     "dwPad": 0,
     "dwMarkerEffectGroupFlags": 0,
     "unk_4bf3f6b": 0,
     "unk_9411612": 0,
     "ptRunTimeMaterialValues": []
    }
   ],
   "ptGroupData": [],
   "ptMarkerLinks": [],
   "unk_c339f69": -1,
   "tIGCHideSettings": {
    "__type__": "MarkerIGCHideSettings",
    "__typeHash__": 867785856,
    "nHideGroup": 0,
    "dwFlags": 0
   },
   "dwSeed": 0,
   "tPrefabData": {
    "__type__": "PrefabData",
    "__typeHash__": 3988626058,
    "dwFlags": 0,
    "eOverrideFadeSettings": 0,
    "eFadeMethod": 0,
    "nFadeGroup": 0,
    "tIGCHideSettings": {
     "__type__": "MarkerIGCHideSettings",
     "__typeHash__": 867785856,
     "nHideGroup": 0,
     "dwFlags": 0
    },
    "eNavBehavior": 0,
    "eCullingLevel": 0,
    "szLookOverride": 0,
    "dwShaderMapOverride": 4294967295,
    "ptRunTimeMaterialValues": []
   }
  },
  {
   "__type__": "Marker",
   "__typeHash__": 3132676386,
   "dwHash": 550982012,
   "nID": 8,
   "eType": 0,
   "transform": {
    "__type__": "PRTransform",
    "__typeHash__": 2588169118,
    "q": {
     "__type__": "bcQuat",
     "__typeHash__": 3955716320,
     "x": 0,
     "y": 0,
     "z": 0.08715648204088211,
     "w": 0.9961946606636047
    },
    "wp": {
     "x": 14.312999725341797,
     "y": 13.76830005645752,
     "z": 10.925100326538086
    }
   },
   "snoname": {
    "__raw__": 371004,
    "__group__": 14,
    "__type__": "DT_SNO_NAME",
    "__typeHash__": 3339108615,
    "__targetFileName__": "base/meta/EffectGroup/environmentVFX_water_aoeDrip.efg",
    "groupName": "EffectGroup",
    "name": "environmentVFX_water_aoeDrip"
   },
   "dwMarkerFlags": 0,
   "dwMarkerFlagsEx": 0,
   "vecScale": {
    "x": 1,
    "y": 1,
    "z": 1
   },
   "ptBase": [
    {
     "__type__": "MarkerEffectGroupData",
     "__typeHash__": 1385267894,
     "dwType": 1385267894,
     "dwPad": 0,
     "dwMarkerEffectGroupFlags": 0,
     "unk_4bf3f6b": 0,
     "unk_9411612": 0,
     "ptRunTimeMaterialValues": []
    }
   ],
   "ptGroupData": [],
   "ptMarkerLinks": [],
   "unk_c339f69": -1,
   "tIGCHideSettings": {
    "__type__": "MarkerIGCHideSettings",
    "__typeHash__": 867785856,
    "nHideGroup": 0,
    "dwFlags": 0
   },
   "dwSeed": 0,
   "tPrefabData": {
    "__type__": "PrefabData",
    "__typeHash__": 3988626058,
    "dwFlags": 0,
    "eOverrideFadeSettings": 0,
    "eFadeMethod": 0,
    "nFadeGroup": 0,
    "tIGCHideSettings": {
     "__type__": "MarkerIGCHideSettings",
     "__typeHash__": 867785856,
     "nHideGroup": 0,
     "dwFlags": 0
    },
    "eNavBehavior": 0,
    "eCullingLevel": 0,
    "szLookOverride": 0,
    "dwShaderMapOverride": 4294967295,
    "ptRunTimeMaterialValues": []
   }
  },
  {
   "__type__": "Marker",
   "__typeHash__": 3132676386,
   "dwHash": 2794349799,
   "nID": 9,
   "eType": 0,
   "transform": {
    "__type__": "PRTransform",
    "__typeHash__": 2588169118,
    "q": {
     "__type__": "bcQuat",
     "__typeHash__": 3955716320,
     "x": 0,
     "y": 0,
     "z": 0,
     "w": 1
    },
    "wp": {
     "x": 18.38599967956543,
     "y": 16.069299697875977,
     "z": -0.3304060101509094
    }
   },
   "snoname": {
    "__raw__": 371060,
    "__group__": 14,
    "__type__": "DT_SNO_NAME",
    "__typeHash__": 3339108615,
    "__targetFileName__": "base/meta/EffectGroup/environmentVFX_flySwarm.efg",
    "groupName": "EffectGroup",
    "name": "environmentVFX_flySwarm"
   },
   "dwMarkerFlags": 0,
   "dwMarkerFlagsEx": 0,
   "vecScale": {
    "x": 1,
    "y": 1,
    "z": 1
   },
   "ptBase": [
    {
     "__type__": "MarkerEffectGroupData",
     "__typeHash__": 1385267894,
     "dwType": 1385267894,
     "dwPad": 0,
     "dwMarkerEffectGroupFlags": 0,
     "unk_4bf3f6b": 0,
     "unk_9411612": 0,
     "ptRunTimeMaterialValues": []
    }
   ],
   "ptGroupData": [],
   "ptMarkerLinks": [],
   "unk_c339f69": -1,
   "tIGCHideSettings": {
    "__type__": "MarkerIGCHideSettings",
    "__typeHash__": 867785856,
    "nHideGroup": 0,
    "dwFlags": 0
   },
   "dwSeed": 0,
   "tPrefabData": {
    "__type__": "PrefabData",
    "__typeHash__": 3988626058,
    "dwFlags": 0,
    "eOverrideFadeSettings": 0,
    "eFadeMethod": 0,
    "nFadeGroup": 0,
    "tIGCHideSettings": {
     "__type__": "MarkerIGCHideSettings",
     "__typeHash__": 867785856,
     "nHideGroup": 0,
     "dwFlags": 0
    },
    "eNavBehavior": 0,
    "eCullingLevel": 0,
    "szLookOverride": 0,
    "dwShaderMapOverride": 4294967295,
    "ptRunTimeMaterialValues": []
   }
  },
  {
   "__type__": "Marker",
   "__typeHash__": 3132676386,
   "dwHash": 2794349800,
   "nID": 10,
   "eType": 0,
   "transform": {
    "__type__": "PRTransform",
    "__typeHash__": 2588169118,
    "q": {
     "__type__": "bcQuat",
     "__typeHash__": 3955716320,
     "x": 0,
     "y": 0,
     "z": 0,
     "w": 1
    },
    "wp": {
     "x": 13.39430046081543,
     "y": 23.35700035095215,
     "z": -1.9693800210952759
    }
   },
   "snoname": {
    "__raw__": 371060,
    "__group__": 14,
    "__type__": "DT_SNO_NAME",
    "__typeHash__": 3339108615,
    "__targetFileName__": "base/meta/EffectGroup/environmentVFX_flySwarm.efg",
    "groupName": "EffectGroup",
    "name": "environmentVFX_flySwarm"
   },
   "dwMarkerFlags": 0,
   "dwMarkerFlagsEx": 0,
   "vecScale": {
    "x": 1,
    "y": 1,
    "z": 1
   },
   "ptBase": [
    {
     "__type__": "MarkerEffectGroupData",
     "__typeHash__": 1385267894,
     "dwType": 1385267894,
     "dwPad": 0,
     "dwMarkerEffectGroupFlags": 0,
     "unk_4bf3f6b": 0,
     "unk_9411612": 0,
     "ptRunTimeMaterialValues": []
    }
   ],
   "ptGroupData": [],
   "ptMarkerLinks": [],
   "unk_c339f69": -1,
   "tIGCHideSettings": {
    "__type__": "MarkerIGCHideSettings",
    "__typeHash__": 867785856,
    "nHideGroup": 0,
    "dwFlags": 0
   },
   "dwSeed": 0,
   "tPrefabData": {
    "__type__": "PrefabData",
    "__typeHash__": 3988626058,
    "dwFlags": 0,
    "eOverrideFadeSettings": 0,
    "eFadeMethod": 0,
    "nFadeGroup": 0,
    "tIGCHideSettings": {
     "__type__": "MarkerIGCHideSettings",
     "__typeHash__": 867785856,
     "nHideGroup": 0,
     "dwFlags": 0
    },
    "eNavBehavior": 0,
    "eCullingLevel": 0,
    "szLookOverride": 0,
    "dwShaderMapOverride": 4294967295,
    "ptRunTimeMaterialValues": []
   }
  },
  {
   "__type__": "Marker",
   "__typeHash__": 3132676386,
   "dwHash": 550982013,
   "nID": 11,
   "eType": 0,
   "transform": {
    "__type__": "PRTransform",
    "__typeHash__": 2588169118,
    "q": {
     "__type__": "bcQuat",
     "__typeHash__": 3955716320,
     "x": 0,
     "y": 0,
     "z": -0.6755900382995605,
     "w": 0.7372775077819824
    },
    "wp": {
     "x": 26.451400756835938,
     "y": 5.793179988861084,
     "z": 7.002110004425049
    }
   },
   "snoname": {
    "__raw__": 371004,
    "__group__": 14,
    "__type__": "DT_SNO_NAME",
    "__typeHash__": 3339108615,
    "__targetFileName__": "base/meta/EffectGroup/environmentVFX_water_aoeDrip.efg",
    "groupName": "EffectGroup",
    "name": "environmentVFX_water_aoeDrip"
   },
   "dwMarkerFlags": 0,
   "dwMarkerFlagsEx": 0,
   "vecScale": {
    "x": 1,
    "y": 1,
    "z": 1
   },
   "ptBase": [
    {
     "__type__": "MarkerEffectGroupData",
     "__typeHash__": 1385267894,
     "dwType": 1385267894,
     "dwPad": 0,
     "dwMarkerEffectGroupFlags": 0,
     "unk_4bf3f6b": 0,
     "unk_9411612": 0,
     "ptRunTimeMaterialValues": []
    }
   ],
   "ptGroupData": [],
   "ptMarkerLinks": [],
   "unk_c339f69": -1,
   "tIGCHideSettings": {
    "__type__": "MarkerIGCHideSettings",
    "__typeHash__": 867785856,
    "nHideGroup": 0,
    "dwFlags": 0
   },
   "dwSeed": 0,
   "tPrefabData": {
    "__type__": "PrefabData",
    "__typeHash__": 3988626058,
    "dwFlags": 0,
    "eOverrideFadeSettings": 0,
    "eFadeMethod": 0,
    "nFadeGroup": 0,
    "tIGCHideSettings": {
     "__type__": "MarkerIGCHideSettings",
     "__typeHash__": 867785856,
     "nHideGroup": 0,
     "dwFlags": 0
    },
    "eNavBehavior": 0,
    "eCullingLevel": 0,
    "szLookOverride": 0,
    "dwShaderMapOverride": 4294967295,
    "ptRunTimeMaterialValues": []
   }
  },
  {
   "__type__": "Marker",
   "__typeHash__": 3132676386,
   "dwHash": 550982014,
   "nID": 12,
   "eType": 0,
   "transform": {
    "__type__": "PRTransform",
    "__typeHash__": 2588169118,
    "q": {
     "__type__": "bcQuat",
     "__typeHash__": 3955716320,
     "x": 0,
     "y": 0,
     "z": -0.13052619993686676,
     "w": 0.9914449453353882
    },
    "wp": {
     "x": 24.201499938964844,
     "y": 9.110790252685547,
     "z": 7.951539993286133
    }
   },
   "snoname": {
    "__raw__": 371004,
    "__group__": 14,
    "__type__": "DT_SNO_NAME",
    "__typeHash__": 3339108615,
    "__targetFileName__": "base/meta/EffectGroup/environmentVFX_water_aoeDrip.efg",
    "groupName": "EffectGroup",
    "name": "environmentVFX_water_aoeDrip"
   },
   "dwMarkerFlags": 0,
   "dwMarkerFlagsEx": 0,
   "vecScale": {
    "x": 1,
    "y": 1,
    "z": 1
   },
   "ptBase": [
    {
     "__type__": "MarkerEffectGroupData",
     "__typeHash__": 1385267894,
     "dwType": 1385267894,
     "dwPad": 0,
     "dwMarkerEffectGroupFlags": 0,
     "unk_4bf3f6b": 0,
     "unk_9411612": 0,
     "ptRunTimeMaterialValues": []
    }
   ],
   "ptGroupData": [],
   "ptMarkerLinks": [],
   "unk_c339f69": -1,
   "tIGCHideSettings": {
    "__type__": "MarkerIGCHideSettings",
    "__typeHash__": 867785856,
    "nHideGroup": 0,
    "dwFlags": 0
   },
   "dwSeed": 0,
   "tPrefabData": {
    "__type__": "PrefabData",
    "__typeHash__": 3988626058,
    "dwFlags": 0,
    "eOverrideFadeSettings": 0,
    "eFadeMethod": 0,
    "nFadeGroup": 0,
    "tIGCHideSettings": {
     "__type__": "MarkerIGCHideSettings",
     "__typeHash__": 867785856,
     "nHideGroup": 0,
     "dwFlags": 0
    },
    "eNavBehavior": 0,
    "eCullingLevel": 0,
    "szLookOverride": 0,
    "dwShaderMapOverride": 4294967295,
    "ptRunTimeMaterialValues": []
   }
  }
 ],
 "dwMarkerSetFlags": 65536,
 "nLabel": null,
 "snoCampaignEnableCondition": null,
 "arPrefabDataInfo": [],
 "ptPrefabDataMap": "0",
 "ptChunks": [],
 "ptMergedMsgTriggeredEvents": [],
 "unk_2bbd1d": {
  "__type__": "Type_c8d78ce7",
  "__typeHash__": 3369569511,
  "nWidth": 0,
  "nHeight": 0,
  "nDepth": 0,
  "dwPitch": 0,
  "dwSlicePitch": 0,
  "flGridSize": 0,
  "wpOrigin": {
   "x": 0,
   "y": 0,
   "z": 0
  },
  "unk_4b236f4": "0",
  "unk_aa0958e": {
   "__type__": "DT_VARIABLEARRAY",
   "__typeHash__": 3244749660,
   "__flags__": 2097153,
   "__external__": true,
   "value": {
    "__typeHash__": 1028759507,
    "__type__": "DT_WORD",
    "dataOffset": 0,
    "dataSize": 0
   }
  },
  "unk_aa09583": {
   "__type__": "DT_VARIABLEARRAY",
   "__typeHash__": 3244749660,
   "__flags__": 2097153,
   "__external__": true,
   "value": {
    "__typeHash__": 1028759507,
    "__type__": "DT_WORD",
    "dataOffset": 0,
    "dataSize": 0
   }
  },
  "unk_aa0957e": {
   "__type__": "DT_VARIABLEARRAY",
   "__typeHash__": 3244749660,
   "__flags__": 2097153,
   "__external__": true,
   "value": {
    "__typeHash__": 1028759507,
    "__type__": "DT_WORD",
    "dataOffset": 0,
    "dataSize": 0
   }
  },
  "unk_dd3cf4b": {
   "__type__": "DT_VARIABLEARRAY",
   "__typeHash__": 3244749660,
   "__flags__": 2097153,
   "__external__": true,
   "value": {
    "__typeHash__": 1028759507,
    "__type__": "DT_WORD",
    "dataOffset": 0,
    "dataSize": 0
   }
  },
  "unk_dd3cf40": {
   "__type__": "DT_VARIABLEARRAY",
   "__typeHash__": 3244749660,
   "__flags__": 2097153,
   "__external__": true,
   "value": {
    "__typeHash__": 1028759507,
    "__type__": "DT_WORD",
    "dataOffset": 0,
    "dataSize": 0
   }
  },
  "unk_dd3cf3b": {
   "__type__": "DT_VARIABLEARRAY",
   "__typeHash__": 3244749660,
   "__flags__": 2097153,
   "__external__": true,
   "value": {
    "__typeHash__": 1028759507,
    "__type__": "DT_WORD",
    "dataOffset": 0,
    "dataSize": 0
   }
  }
 }
}
